{
  "errno": 0,
  "request_id": 178039588523191218,
  "server_time": 1766388820,
  "cfrom_id": 0,
  "hitrisk": 0,
  "appeal_status": 0,
  "is_zombie": 0,
  "vip_point": 5,
  "vip_level": 1,
  "svip10_id": "",
  "vip_type": 0,
  "sharetype": 0,
  "view_visited": 0,
  "view_limit": 0,
  "expired_type": 0,
  "title": "/Z-指尖浪漫",
  "list": [
    {
      "category": "6",
      "extent_int8": "0",
      "fs_id": "815220385667341",
      "isdir": "1",
      "local_ctime": "1739022128",
      "local_mtime": "1739022128",
      "md5": "",
      "path": "/Z-指尖浪漫",
      "server_ctime": "1739022128",
      "server_filename": "Z-指尖浪漫",
      "server_mtime": "1742698964",
      "size": "0"
    }
  ],
  "share_id": 8274759800,
  "uk": 1743324397,
  "show_msg": "success"
}